{
    "id": "075316",
    "case_type": "緊急救護",
    "location": "台南市麻豆區",
    "unit": "玉井分隊",
    "history": [
        {
            "datetime": "2025/10/23 07:53:16",
            "status": "已派遣",
            "updated": "2025/10/23 07:55:04"
        },
        {
            "datetime": "2025/10/23 07:53:16",
            "status": "已到達",
            "updated": "2025/10/23 08:00:04"
        },
        {
            "datetime": "2025/10/23 07:53:16",
            "status": "返隊中",
            "updated": "2025/10/23 08:30:04"
        },
        {
            "datetime": "2025/10/23 07:53:16",
            "status": "已返隊",
            "updated": "2025/10/23 08:35:04"
        }
    ]
}