{
    "id": "211426",
    "case_type": "火災",
    "location": "台南市中西區西寧街",
    "unit": "中正分隊,公園分隊,南門分隊,和緯分隊,安平分隊,永華分隊,第六大隊",
    "history": [
        {
            "datetime": "2025/09/21 21:14:26",
            "status": "已出動",
            "updated": "2025/09/21 21:20:04"
        },
        {
            "datetime": "2025/09/21 21:14:26",
            "status": "已到達",
            "updated": "2025/09/21 21:25:03"
        },
        {
            "datetime": "2025/09/21 21:14:26",
            "status": "火已滅",
            "updated": "2025/09/21 21:45:04"
        },
        {
            "datetime": "2025/09/21 21:14:26",
            "status": "返隊中",
            "updated": "2025/09/21 21:55:04"
        }
    ]
}