{
    "id": "073345",
    "case_type": "緊急救護",
    "location": "台南市麻豆區",
    "unit": "善化分隊",
    "history": [
        {
            "datetime": "2025/11/06 07:33:45",
            "status": "已派遣",
            "updated": "2025/11/06 07:35:04"
        },
        {
            "datetime": "2025/11/06 07:33:45",
            "status": "送醫中",
            "updated": "2025/11/06 07:50:04"
        },
        {
            "datetime": "2025/11/06 07:33:45",
            "status": "已到院",
            "updated": "2025/11/06 07:55:04"
        },
        {
            "datetime": "2025/11/06 07:33:45",
            "status": "返隊中",
            "updated": "2025/11/06 08:05:05"
        }
    ]
}