{
    "id": "094031",
    "case_type": "緊急救護",
    "location": "台南市永康區",
    "unit": "永康分隊",
    "history": [
        {
            "datetime": "2025/08/19 09:40:31",
            "status": "已出動",
            "updated": "2025/08/19 09:45:04"
        },
        {
            "datetime": "2025/08/19 09:40:31",
            "status": "已到達",
            "updated": "2025/08/19 09:55:04"
        },
        {
            "datetime": "2025/08/19 09:40:31",
            "status": "送醫中",
            "updated": "2025/08/19 10:05:04"
        },
        {
            "datetime": "2025/08/19 09:40:31",
            "status": "已到院",
            "updated": "2025/08/19 10:10:04"
        },
        {
            "datetime": "2025/08/19 09:40:31",
            "status": "返隊中",
            "updated": "2025/08/19 11:20:03"
        }
    ]
}