{
    "id": "165339",
    "case_type": "火災",
    "location": "台南市後壁區",
    "unit": "後壁分隊",
    "history": [
        {
            "datetime": "2025/11/08 16:53:39",
            "status": "已出動",
            "updated": "2025/11/08 17:00:04"
        },
        {
            "datetime": "2025/11/08 16:53:39",
            "status": "已到達",
            "updated": "2025/11/08 17:10:04"
        },
        {
            "datetime": "2025/11/08 16:53:39",
            "status": "返隊中",
            "updated": "2025/11/08 17:15:04"
        },
        {
            "datetime": "2025/11/08 16:53:39",
            "status": "已返隊",
            "updated": "2025/11/08 18:00:03"
        }
    ]
}