{
    "id": "112009",
    "case_type": "緊急救護",
    "location": "台南市東區",
    "unit": "崇善分隊",
    "history": [
        {
            "datetime": "2025/08/13 11:20:09",
            "status": "已派遣",
            "updated": "2025/08/13 11:25:04"
        },
        {
            "datetime": "2025/08/13 11:20:09",
            "status": "已到達",
            "updated": "2025/08/13 11:30:04"
        },
        {
            "datetime": "2025/08/13 11:20:09",
            "status": "已到院",
            "updated": "2025/08/13 11:40:04"
        },
        {
            "datetime": "2025/08/13 11:20:09",
            "status": "返隊中",
            "updated": "2025/08/13 12:10:04"
        },
        {
            "datetime": "2025/08/13 11:20:09",
            "status": "已返隊",
            "updated": "2025/08/13 12:15:04"
        }
    ]
}