{
    "id": "082608",
    "case_type": "緊急救護",
    "location": "台南市仁德區",
    "unit": "仁德分隊",
    "history": [
        {
            "datetime": "2025/11/05 08:26:12",
            "status": "已派遣",
            "updated": "2025/11/05 08:30:04"
        },
        {
            "datetime": "2025/11/05 08:26:12",
            "status": "已到達",
            "updated": "2025/11/05 08:40:04"
        },
        {
            "datetime": "2025/11/05 08:26:12",
            "status": "送醫中",
            "updated": "2025/11/05 08:50:04"
        },
        {
            "datetime": "2025/11/05 08:26:12",
            "status": "已到院",
            "updated": "2025/11/05 09:05:04"
        },
        {
            "datetime": "2025/11/05 08:26:12",
            "status": "返隊中",
            "updated": "2025/11/05 09:35:03"
        },
        {
            "datetime": "2025/11/05 08:26:12",
            "status": "已返隊",
            "updated": "2025/11/05 10:25:04"
        }
    ]
}