{
    "id": "062930",
    "case_type": "緊急救護",
    "location": "台南市東區",
    "unit": "東門分隊",
    "history": [
        {
            "datetime": "2025/08/05 06:29:33",
            "status": "已派遣",
            "updated": "2025/08/05 06:35:04"
        },
        {
            "datetime": "2025/08/05 06:29:33",
            "status": "已到達",
            "updated": "2025/08/05 06:40:03"
        },
        {
            "datetime": "2025/08/05 06:29:33",
            "status": "返隊中",
            "updated": "2025/08/05 06:55:04"
        }
    ]
}