{
    "id": "184946",
    "case_type": "緊急救護",
    "location": "台南市仁德區",
    "unit": "仁德分隊",
    "history": [
        {
            "datetime": "2025/12/11 18:49:46",
            "status": "已派遣",
            "updated": "2025/12/11 18:50:04"
        },
        {
            "datetime": "2025/12/11 18:49:46",
            "status": "已到達",
            "updated": "2025/12/11 19:00:04"
        },
        {
            "datetime": "2025/12/11 18:49:46",
            "status": "送醫中",
            "updated": "2025/12/11 19:20:04"
        },
        {
            "datetime": "2025/12/11 18:49:46",
            "status": "已到院",
            "updated": "2025/12/11 19:25:04"
        },
        {
            "datetime": "2025/12/11 18:49:46",
            "status": "返隊中",
            "updated": "2025/12/11 20:00:04"
        }
    ]
}