{
    "id": "034805",
    "case_type": "緊急救護",
    "location": "台南市佳里區",
    "unit": "佳里分隊",
    "history": [
        {
            "datetime": "2025/08/11 03:48:05",
            "status": "已出動",
            "updated": "2025/08/11 03:50:04"
        },
        {
            "datetime": "2025/08/11 03:48:05",
            "status": "送醫中",
            "updated": "2025/08/11 04:00:04"
        },
        {
            "datetime": "2025/08/11 03:48:05",
            "status": "已到院",
            "updated": "2025/08/11 04:15:04"
        },
        {
            "datetime": "2025/08/11 03:48:05",
            "status": "返隊中",
            "updated": "2025/08/11 04:40:04"
        },
        {
            "datetime": "2025/08/11 03:48:05",
            "status": "已返隊",
            "updated": "2025/08/11 05:05:04"
        }
    ]
}