{
    "id": "162912",
    "case_type": "緊急救護",
    "location": "台南市中西區",
    "unit": "中正分隊",
    "history": [
        {
            "datetime": "2025/08/04 16:29:18",
            "status": "已派遣",
            "updated": "2025/08/04 16:30:04"
        },
        {
            "datetime": "2025/08/04 16:29:18",
            "status": "已到達",
            "updated": "2025/08/04 16:35:04"
        },
        {
            "datetime": "2025/08/04 16:29:18",
            "status": "送醫中",
            "updated": "2025/08/04 16:45:04"
        }
    ]
}