{
    "id": "121950",
    "case_type": "緊急救護",
    "location": "台南市安平區",
    "unit": "安平分隊",
    "history": [
        {
            "datetime": "2026/01/04 12:19:50",
            "status": "已出動",
            "updated": "2026/01/04 12:25:04"
        },
        {
            "datetime": "2026/01/04 12:19:50",
            "status": "已到達",
            "updated": "2026/01/04 12:40:05"
        },
        {
            "datetime": "2026/01/04 12:19:50",
            "status": "已到院",
            "updated": "2026/01/04 13:10:38"
        }
    ]
}