{
    "id": "103554",
    "case_type": "緊急救護",
    "location": "台南市東區",
    "unit": "東門分隊",
    "history": [
        {
            "datetime": "2026/01/24 10:35:58",
            "status": "已派遣",
            "updated": "2026/01/24 10:40:04"
        },
        {
            "datetime": "2026/01/24 10:35:58",
            "status": "已到達",
            "updated": "2026/01/24 10:45:04"
        },
        {
            "datetime": "2026/01/24 10:35:58",
            "status": "返隊中",
            "updated": "2026/01/24 10:55:04"
        },
        {
            "datetime": "2026/01/24 10:35:58",
            "status": "已返隊",
            "updated": "2026/01/24 11:20:04"
        }
    ]
}