{
    "id": "083654",
    "case_type": "緊急救護",
    "location": "台南市永康區",
    "unit": "鹽行分隊",
    "history": [
        {
            "datetime": "2025/08/05 08:36:54",
            "status": "已派遣",
            "updated": "2025/08/05 08:40:04"
        },
        {
            "datetime": "2025/08/05 08:36:54",
            "status": "已到達",
            "updated": "2025/08/05 08:45:04"
        },
        {
            "datetime": "2025/08/05 08:36:54",
            "status": "送醫中",
            "updated": "2025/08/05 09:00:04"
        },
        {
            "datetime": "2025/08/05 08:36:54",
            "status": "已到院",
            "updated": "2025/08/05 09:05:04"
        },
        {
            "datetime": "2025/08/05 08:36:54",
            "status": "返隊中",
            "updated": "2025/08/05 09:20:04"
        }
    ]
}