{
    "id": "172106",
    "case_type": "緊急救護",
    "location": "台南市鹽水區",
    "unit": "鹽水分隊",
    "history": [
        {
            "datetime": "2025/10/24 17:21:06",
            "status": "已派遣",
            "updated": "2025/10/24 17:24:51"
        },
        {
            "datetime": "2025/10/24 17:21:06",
            "status": "已到達",
            "updated": "2025/10/24 17:31:15"
        },
        {
            "datetime": "2025/10/24 17:21:06",
            "status": "送醫中",
            "updated": "2025/10/24 17:41:42"
        },
        {
            "datetime": "2025/10/24 17:21:06",
            "status": "已到院",
            "updated": "2025/10/24 18:00:11"
        },
        {
            "datetime": "2025/10/24 17:21:06",
            "status": "返隊中",
            "updated": "2025/10/24 18:20:04"
        },
        {
            "datetime": "2025/10/24 17:21:06",
            "status": "已返隊",
            "updated": "2025/10/24 18:40:04"
        }
    ]
}