{
    "id": "142719",
    "case_type": "火災",
    "location": "台南市南區西門路一段",
    "unit": "南門分隊",
    "history": [
        {
            "datetime": "2025/10/22 14:27:19",
            "status": "已派遣",
            "updated": "2025/10/22 14:30:04"
        },
        {
            "datetime": "2025/10/22 14:27:19",
            "status": "已到達",
            "updated": "2025/10/22 14:40:04"
        },
        {
            "datetime": "2025/10/22 14:27:19",
            "status": "返隊中",
            "updated": "2025/10/22 14:45:04"
        },
        {
            "datetime": "2025/10/22 14:27:19",
            "status": "已返隊",
            "updated": "2025/10/22 14:50:04"
        }
    ]
}