{
    "id": "004723",
    "case_type": "緊急救護",
    "location": "台南市安定區",
    "unit": "安定分隊",
    "history": [
        {
            "datetime": "2025/08/10 00:47:23",
            "status": "已出動",
            "updated": "2025/08/10 00:50:04"
        },
        {
            "datetime": "2025/08/10 00:47:23",
            "status": "送醫中",
            "updated": "2025/08/10 01:00:05"
        },
        {
            "datetime": "2025/08/10 00:47:23",
            "status": "已到院",
            "updated": "2025/08/10 01:10:04"
        }
    ]
}