{
    "id": "145842",
    "case_type": "緊急救護",
    "location": "台南市北區",
    "unit": "公園分隊",
    "history": [
        {
            "datetime": "2025/11/14 14:58:42",
            "status": "已出動",
            "updated": "2025/11/14 15:00:04"
        },
        {
            "datetime": "2025/11/14 14:58:42",
            "status": "已到達",
            "updated": "2025/11/14 15:05:04"
        },
        {
            "datetime": "2025/11/14 14:58:42",
            "status": "送醫中",
            "updated": "2025/11/14 15:30:04"
        },
        {
            "datetime": "2025/11/14 14:58:42",
            "status": "已到院",
            "updated": "2025/11/14 15:35:04"
        },
        {
            "datetime": "2025/11/14 14:58:42",
            "status": "返隊中",
            "updated": "2025/11/14 16:00:04"
        },
        {
            "datetime": "2025/11/14 14:58:42",
            "status": "已返隊",
            "updated": "2025/11/14 16:45:04"
        }
    ]
}