{
    "id": "170437",
    "case_type": "緊急救護",
    "location": "台南市南區",
    "unit": "德興分隊",
    "history": [
        {
            "datetime": "2025/11/29 17:04:37",
            "status": "已出動",
            "updated": "2025/11/29 17:10:04"
        },
        {
            "datetime": "2025/11/29 17:04:37",
            "status": "已到達",
            "updated": "2025/11/29 17:15:04"
        },
        {
            "datetime": "2025/11/29 17:04:37",
            "status": "送醫中",
            "updated": "2025/11/29 17:20:04"
        },
        {
            "datetime": "2025/11/29 17:04:37",
            "status": "已到院",
            "updated": "2025/11/29 17:30:03"
        }
    ]
}