{
    "id": "165608",
    "case_type": "緊急救護",
    "location": "台南市永康區",
    "unit": "大橋高救",
    "history": [
        {
            "datetime": "2025/08/12 16:56:08",
            "status": "已派遣",
            "updated": "2025/08/12 17:00:04"
        },
        {
            "datetime": "2025/08/12 16:56:08",
            "status": "已到達",
            "updated": "2025/08/12 17:05:04"
        },
        {
            "datetime": "2025/08/12 16:56:08",
            "status": "送醫中",
            "updated": "2025/08/12 17:30:04"
        }
    ]
}