{
    "id": "125741",
    "case_type": "緊急救護",
    "location": "台南市麻豆區",
    "unit": "麻豆分隊",
    "history": [
        {
            "datetime": "2025/08/15 12:57:41",
            "status": "已派遣",
            "updated": "2025/08/15 13:00:04"
        },
        {
            "datetime": "2025/08/15 12:57:41",
            "status": "已到達",
            "updated": "2025/08/15 13:05:04"
        },
        {
            "datetime": "2025/08/15 12:57:41",
            "status": "送醫中",
            "updated": "2025/08/15 13:20:04"
        },
        {
            "datetime": "2025/08/15 12:57:41",
            "status": "已到院",
            "updated": "2025/08/15 13:25:04"
        },
        {
            "datetime": "2025/08/15 12:57:41",
            "status": "已返隊",
            "updated": "2025/08/15 13:40:04"
        }
    ]
}