{
    "id": "154546",
    "case_type": "緊急救護",
    "location": "台南市北區",
    "unit": "和緯分隊",
    "history": [
        {
            "datetime": "2025/08/15 15:45:46",
            "status": "已出動",
            "updated": "2025/08/15 15:50:04"
        },
        {
            "datetime": "2025/08/15 15:45:46",
            "status": "送醫中",
            "updated": "2025/08/15 15:55:04"
        },
        {
            "datetime": "2025/08/15 15:45:46",
            "status": "已到院",
            "updated": "2025/08/15 16:05:04"
        },
        {
            "datetime": "2025/08/15 15:45:46",
            "status": "返隊中",
            "updated": "2025/08/15 16:15:04"
        }
    ]
}