{
    "id": "072626",
    "case_type": "緊急救護",
    "location": "台南市仁德區",
    "unit": "仁德分隊",
    "history": [
        {
            "datetime": "2026/01/15 07:26:26",
            "status": "已出動",
            "updated": "2026/01/15 07:30:04"
        },
        {
            "datetime": "2026/01/15 07:26:26",
            "status": "已到達",
            "updated": "2026/01/15 07:35:04"
        },
        {
            "datetime": "2026/01/15 07:26:26",
            "status": "返隊中",
            "updated": "2026/01/15 07:50:04"
        }
    ]
}