{
    "id": "081949",
    "case_type": "緊急救護",
    "location": "台南市鹽水區",
    "unit": "鹽水分隊",
    "history": [
        {
            "datetime": "2026/06/18 08:19:49",
            "status": "已出動",
            "updated": "2026/06/18 08:25:05"
        },
        {
            "datetime": "2026/06/18 08:19:49",
            "status": "已到達",
            "updated": "2026/06/18 08:30:06"
        },
        {
            "datetime": "2026/06/18 08:19:49",
            "status": "送醫中",
            "updated": "2026/06/18 08:35:06"
        },
        {
            "datetime": "2026/06/18 08:19:49",
            "status": "已到院",
            "updated": "2026/06/18 08:45:07"
        },
        {
            "datetime": "2026/06/18 08:19:49",
            "status": "返隊中",
            "updated": "2026/06/18 08:50:05"
        }
    ]
}