{
    "id": "205529",
    "case_type": "緊急救護",
    "location": "台南市安南區",
    "unit": "安南分隊",
    "history": [
        {
            "datetime": "2025/08/02 20:55:29",
            "status": "已出動",
            "updated": "2025/08/02 21:00:04"
        },
        {
            "datetime": "2025/08/02 20:55:29",
            "status": "已到達",
            "updated": "2025/08/02 21:05:04"
        },
        {
            "datetime": "2025/08/02 20:55:29",
            "status": "送醫中",
            "updated": "2025/08/02 21:10:04"
        }
    ]
}