{
    "id": "073647",
    "case_type": "緊急救護",
    "location": "台南市安南區",
    "unit": "土城分隊",
    "history": [
        {
            "datetime": "2025/11/06 07:36:50",
            "status": "已出動",
            "updated": "2025/11/06 07:40:04"
        },
        {
            "datetime": "2025/11/06 07:36:50",
            "status": "已到達",
            "updated": "2025/11/06 07:55:04"
        },
        {
            "datetime": "2025/11/06 07:36:50",
            "status": "返隊中",
            "updated": "2025/11/06 08:05:05"
        }
    ]
}