{
    "id": "191610",
    "case_type": "火災",
    "location": "台南市西港區",
    "unit": "七股分隊,佳里分隊,安定分隊,將軍分隊,第三大隊,西港分隊",
    "history": [
        {
            "datetime": "2025/08/19 19:16:10",
            "status": "已出動",
            "updated": "2025/08/19 19:20:04"
        },
        {
            "datetime": "2025/08/19 19:16:10",
            "status": "已到達",
            "updated": "2025/08/19 19:25:05"
        },
        {
            "datetime": "2025/08/19 19:16:10",
            "status": "返隊中",
            "updated": "2025/08/19 19:30:04"
        },
        {
            "datetime": "2025/08/19 19:16:10",
            "status": "已返隊",
            "updated": "2025/08/19 19:50:04"
        }
    ]
}