[
    {
        "id": "085734",
        "datetime": "2025/08/21 08:57:34",
        "case_type": "緊急救護",
        "location": "台南市中西區",
        "unit": "永華分隊",
        "status": "已出動"
    },
    {
        "id": "085224",
        "datetime": "2025/08/21 08:52:24",
        "case_type": "緊急救護",
        "location": "台南市北區",
        "unit": "和緯分隊",
        "status": "已出動"
    },
    {
        "id": "085127",
        "datetime": "2025/08/21 08:51:27",
        "case_type": "緊急救護",
        "location": "台南市永康區",
        "unit": "永康分隊,鹽行分隊",
        "status": "已出動"
    },
    {
        "id": "085034",
        "datetime": "2025/08/21 08:52:56",
        "case_type": "緊急救護",
        "location": "台南市永康區",
        "unit": "大灣分隊",
        "status": "已派遣"
    },
    {
        "id": "085026",
        "datetime": "2025/08/21 08:50:26",
        "case_type": "緊急救護",
        "location": "台南市安南區",
        "unit": "土城分隊",
        "status": "已到達"
    },
    {
        "id": "084914",
        "datetime": "2025/08/21 08:49:14",
        "case_type": "緊急救護",
        "location": "台南市南區",
        "unit": "德興分隊",
        "status": "已到達"
    },
    {
        "id": "084644",
        "datetime": "2025/08/21 08:46:44",
        "case_type": "緊急救護",
        "location": "台南市關廟區",
        "unit": "關廟分隊",
        "status": "送醫中"
    },
    {
        "id": "084644",
        "datetime": "2025/08/21 08:46:44",
        "case_type": "緊急救護",
        "location": "台南市鹽水區",
        "unit": "柳營分隊,鹽水分隊",
        "status": "返隊中"
    },
    {
        "id": "084403",
        "datetime": "2025/08/21 08:44:03",
        "case_type": "緊急救護",
        "location": "台南市新市區",
        "unit": "新市分隊",
        "status": "已到達"
    },
    {
        "id": "084217",
        "datetime": "2025/08/21 08:42:17",
        "case_type": "緊急救護",
        "location": "台南市安南區",
        "unit": "安南分隊",
        "status": "已返隊"
    },
    {
        "id": "083724",
        "datetime": "2025/08/21 08:37:24",
        "case_type": "緊急救護",
        "location": "台南市永康區",
        "unit": "大橋高救",
        "status": "已到達"
    },
    {
        "id": "083126",
        "datetime": "2025/08/21 08:31:26",
        "case_type": "其他",
        "location": "台南市新市區台南市消防局新市分隊[台南市新市區民生路",
        "unit": "第四大隊",
        "status": ""
    },
    {
        "id": "083123",
        "datetime": "2025/08/21 08:31:23",
        "case_type": "緊急救護",
        "location": "台南市仁德區",
        "unit": "後甲分隊",
        "status": "已返隊"
    },
    {
        "id": "082623",
        "datetime": "2025/08/21 08:26:23",
        "case_type": "緊急救護",
        "location": "台南市安平區",
        "unit": "永華分隊",
        "status": "已到院"
    },
    {
        "id": "082457",
        "datetime": "2025/08/21 08:24:57",
        "case_type": "緊急救護",
        "location": "台南市仁德區",
        "unit": "仁德分隊",
        "status": "已到院"
    },
    {
        "id": "082443",
        "datetime": "2025/08/21 08:24:43",
        "case_type": "緊急救護",
        "location": "台南市七股區",
        "unit": "七股分隊",
        "status": "已到院"
    },
    {
        "id": "082241",
        "datetime": "2025/08/21 08:22:41",
        "case_type": "緊急救護",
        "location": "台南市北區",
        "unit": "公園分隊",
        "status": "已到院"
    },
    {
        "id": "082106",
        "datetime": "2025/08/21 08:21:06",
        "case_type": "其他",
        "location": "台南市新市區",
        "unit": "佳里分隊",
        "status": "已出動"
    },
    {
        "id": "081929",
        "datetime": "2025/08/21 08:19:29",
        "case_type": "緊急救護",
        "location": "台南市永康區",
        "unit": "鹽行分隊",
        "status": "返隊中"
    },
    {
        "id": "080616",
        "datetime": "2025/08/21 08:06:16",
        "case_type": "緊急救護",
        "location": "台南市鹽水區",
        "unit": "鹽水分隊",
        "status": "返隊中"
    },
    {
        "id": "080455",
        "datetime": "2025/08/21 08:05:55",
        "case_type": "緊急救護",
        "location": "台南市龍崎區",
        "unit": "保西分隊",
        "status": "送醫中"
    },
    {
        "id": "075325",
        "datetime": "2025/08/21 07:53:25",
        "case_type": "緊急救護",
        "location": "台南市麻豆區",
        "unit": "麻豆分隊",
        "status": "已到院"
    },
    {
        "id": "075130",
        "datetime": "2025/08/21 07:51:30",
        "case_type": "緊急救護",
        "location": "台南市永康區",
        "unit": "大橋高救",
        "status": "已返隊"
    },
    {
        "id": "074030",
        "datetime": "2025/08/21 07:40:30",
        "case_type": "緊急救護",
        "location": "台南市東區",
        "unit": "崇善分隊",
        "status": "返隊中"
    },
    {
        "id": "073205",
        "datetime": "2025/08/21 07:32:05",
        "case_type": "緊急救護",
        "location": "台南市永康區",
        "unit": "大灣分隊",
        "status": "已返隊"
    },
    {
        "id": "072613",
        "datetime": "2025/08/21 07:26:13",
        "case_type": "緊急救護",
        "location": "台南市新市區",
        "unit": "新市分隊",
        "status": "已返隊"
    },
    {
        "id": "072154",
        "datetime": "2025/08/21 07:21:54",
        "case_type": "緊急救護",
        "location": "台南市關廟區",
        "unit": "關廟分隊",
        "status": "已返隊"
    },
    {
        "id": "064654",
        "datetime": "2025/08/21 06:46:54",
        "case_type": "緊急救護",
        "location": "台南市將軍區",
        "unit": "學甲分隊",
        "status": "已返隊"
    },
    {
        "id": "000935",
        "datetime": "2025/08/20 00:09:46",
        "case_type": "災害搶救",
        "location": "台南市安平區",
        "unit": "和緯分隊,安平分隊,永華分隊",
        "status": "已返隊"
    },
    {
        "id": "205524",
        "datetime": "2025/08/19 20:55:24",
        "case_type": "緊急救護",
        "location": "台南市安定區",
        "unit": "南科分隊,安定分隊,第四大隊,西港分隊",
        "status": "已返隊"
    },
    {
        "id": "102137",
        "datetime": "2025/08/19 10:21:37",
        "case_type": "其他",
        "location": "(失蹤協尋)台南市仁德區中洲七街",
        "unit": "大橋特搜分隊,文賢分隊,歸仁分隊,第五大隊",
        "status": "已返隊"
    },
    {
        "id": "040827",
        "datetime": "2025/08/05 04:08:27",
        "case_type": "火災",
        "location": "台南市安定區",
        "unit": "佳里分隊,六甲分隊,南科分隊,善化分隊,大橋特搜分隊,學甲分隊,安南分隊,安和分隊,安定分隊,新市分隊,第四大隊,西港分隊",
        "status": "已返隊"
    },
    {
        "id": "151454",
        "datetime": "2025/07/24 15:14:54",
        "case_type": "災害搶救",
        "location": "台南市南區濱南路",
        "unit": "中正分隊,南門分隊,大橋特搜分隊,安南分隊,崇善分隊,後甲分隊,復興分隊,德興分隊,東門分隊,永華分隊,灣裡分隊,第七大隊,第六大隊",
        "status": "已返隊"
    }
]