[
    {
        "id": "080832",
        "datetime": "2026/04/14 08:08:32",
        "case_type": "緊急救護",
        "location": "台南市麻豆區",
        "unit": "麻豆分隊",
        "status": "已派遣"
    },
    {
        "id": "080546",
        "datetime": "2026/04/14 08:05:48",
        "case_type": "緊急救護",
        "location": "台南市南區",
        "unit": "南門分隊",
        "status": "已出動"
    },
    {
        "id": "080232",
        "datetime": "2026/04/14 08:02:32",
        "case_type": "緊急救護",
        "location": "台南市仁德區",
        "unit": "歸仁分隊",
        "status": "已出動"
    },
    {
        "id": "080120",
        "datetime": "2026/04/14 08:01:20",
        "case_type": "緊急救護",
        "location": "台南市玉井區",
        "unit": "玉井分隊",
        "status": "已到達"
    },
    {
        "id": "075840",
        "datetime": "2026/04/14 07:58:45",
        "case_type": "緊急救護",
        "location": "台南市善化區",
        "unit": "新市分隊",
        "status": "已出動"
    },
    {
        "id": "075735",
        "datetime": "2026/04/14 07:57:35",
        "case_type": "緊急救護",
        "location": "台南市東區",
        "unit": "崇善分隊",
        "status": "已到達"
    },
    {
        "id": "075545",
        "datetime": "2026/04/14 07:55:45",
        "case_type": "緊急救護",
        "location": "台南市東區",
        "unit": "東門分隊",
        "status": "已出動"
    },
    {
        "id": "075144",
        "datetime": "2026/04/14 07:51:44",
        "case_type": "緊急救護",
        "location": "台南市官田區",
        "unit": "官田分隊",
        "status": "已到達"
    },
    {
        "id": "075031",
        "datetime": "2026/04/14 07:50:31",
        "case_type": "緊急救護",
        "location": "台南市楠西區",
        "unit": "楠西分隊",
        "status": "已到達"
    },
    {
        "id": "073952",
        "datetime": "2026/04/14 07:39:52",
        "case_type": "緊急救護",
        "location": "台南市中西區",
        "unit": "中正分隊",
        "status": "返隊中"
    },
    {
        "id": "073937",
        "datetime": "2026/04/14 07:39:37",
        "case_type": "緊急救護",
        "location": "台南市鹽水區",
        "unit": "鹽水分隊",
        "status": "已到院"
    },
    {
        "id": "073726",
        "datetime": "2026/04/14 07:37:26",
        "case_type": "緊急救護",
        "location": "台南市六甲區",
        "unit": "六甲分隊",
        "status": "送醫中"
    },
    {
        "id": "073605",
        "datetime": "2026/04/14 07:36:08",
        "case_type": "緊急救護",
        "location": "台南市永康區",
        "unit": "公園分隊,復興分隊",
        "status": "已到院"
    },
    {
        "id": "073308",
        "datetime": "2026/04/14 07:33:08",
        "case_type": "緊急救護",
        "location": "台南市學甲區",
        "unit": "學甲分隊",
        "status": "送醫中"
    },
    {
        "id": "073146",
        "datetime": "2026/04/14 07:31:46",
        "case_type": "緊急救護",
        "location": "台南市永康區",
        "unit": "大橋高救",
        "status": "已到院"
    },
    {
        "id": "072702",
        "datetime": "2026/04/14 07:27:02",
        "case_type": "緊急救護",
        "location": "台南市善化區",
        "unit": "善化分隊",
        "status": "已到院"
    },
    {
        "id": "072605",
        "datetime": "2026/04/14 07:26:07",
        "case_type": "緊急救護",
        "location": "台南市南區",
        "unit": "灣裡分隊",
        "status": "返隊中"
    },
    {
        "id": "072547",
        "datetime": "2026/04/14 07:25:47",
        "case_type": "緊急救護",
        "location": "台南市後壁區",
        "unit": "後壁分隊",
        "status": "送醫中"
    },
    {
        "id": "071027",
        "datetime": "2026/04/14 07:10:27",
        "case_type": "緊急救護",
        "location": "台南市永康區",
        "unit": "安和分隊,鹽行分隊",
        "status": "返隊中"
    },
    {
        "id": "070454",
        "datetime": "2026/04/14 07:04:54",
        "case_type": "緊急救護",
        "location": "台南市仁德區",
        "unit": "文賢分隊",
        "status": "返隊中"
    },
    {
        "id": "065802",
        "datetime": "2026/04/14 06:58:02",
        "case_type": "緊急救護",
        "location": "台南市安南區",
        "unit": "安南分隊",
        "status": "返隊中"
    },
    {
        "id": "065632",
        "datetime": "2026/04/14 06:57:32",
        "case_type": "緊急救護",
        "location": "台南市新市區",
        "unit": "南科分隊",
        "status": "返隊中"
    },
    {
        "id": "064208",
        "datetime": "2026/04/14 06:42:16",
        "case_type": "緊急救護",
        "location": "台南市新化區",
        "unit": "新化分隊",
        "status": "返隊中"
    },
    {
        "id": "014957",
        "datetime": "2026/04/14 01:50:00",
        "case_type": "緊急救護",
        "location": "台南市麻豆區",
        "unit": "下營分隊,善化分隊,官田分隊,麻豆分隊",
        "status": "已返隊"
    },
    {
        "id": "010247",
        "datetime": "2026/04/14 01:02:47",
        "case_type": "火災",
        "location": "台南市永康區大灣路",
        "unit": "仁德分隊,保西分隊,和緯分隊,大橋特搜分隊,大橋高救,大灣分隊,後甲分隊,復興分隊,東門分隊,永康分隊,特搜大隊,第五大隊",
        "status": "已返隊"
    },
    {
        "id": "130722",
        "datetime": "2026/04/13 13:07:22",
        "case_type": "火災",
        "location": "台南市佳里區文化路483巷",
        "unit": "七股分隊,佳里分隊,北門分隊,學甲分隊,將軍分隊,第三大隊,西港分隊,麻豆分隊",
        "status": "已返隊"
    }
]