[
    {
        "id": "070100",
        "datetime": "2025/06/20 07:01:10",
        "case_type": "緊急救護",
        "location": "台南市關廟區",
        "unit": "大橋特搜分隊,歸仁分隊,關廟分隊",
        "status": "已出動"
    },
    {
        "id": "065719",
        "datetime": "2025/06/20 06:57:19",
        "case_type": "緊急救護",
        "location": "台南市南區",
        "unit": "永華分隊",
        "status": ""
    },
    {
        "id": "063911",
        "datetime": "2025/06/20 06:39:22",
        "case_type": "緊急救護",
        "location": "台南市南區",
        "unit": "德興分隊",
        "status": "送醫中"
    },
    {
        "id": "063638",
        "datetime": "2025/06/20 06:36:38",
        "case_type": "緊急救護",
        "location": "台南市西港區",
        "unit": "西港分隊",
        "status": "已到達"
    },
    {
        "id": "140532",
        "datetime": "2025/06/19 14:08:32",
        "case_type": "其他",
        "location": "台南市東區中華東路三段77巷",
        "unit": "崇善分隊,後甲分隊",
        "status": "已返隊"
    },
    {
        "id": "142144",
        "datetime": "2025/06/06 14:21:47",
        "case_type": "其他",
        "location": "台南市將軍區",
        "unit": "將軍分隊",
        "status": "已返隊"
    }
]