[
    {
        "id": "203359",
        "datetime": "2026/02/26 20:33:59",
        "case_type": "緊急救護",
        "location": "台南市東區",
        "unit": "崇善分隊",
        "status": "送醫中"
    },
    {
        "id": "203210",
        "datetime": "2026/02/26 20:32:10",
        "case_type": "緊急救護",
        "location": "台南市安定區",
        "unit": "南科分隊",
        "status": "已到達"
    },
    {
        "id": "202434",
        "datetime": "2026/02/26 20:24:34",
        "case_type": "緊急救護",
        "location": "台南市歸仁區",
        "unit": "仁德分隊",
        "status": "送醫中"
    },
    {
        "id": "201413",
        "datetime": "2026/02/26 20:14:13",
        "case_type": "緊急救護",
        "location": "台南市安定區",
        "unit": "安定分隊",
        "status": "送醫中"
    },
    {
        "id": "200829",
        "datetime": "2026/02/26 20:08:29",
        "case_type": "緊急救護",
        "location": "台南市南化區",
        "unit": "南化分隊",
        "status": "送醫中"
    },
    {
        "id": "200546",
        "datetime": "2026/02/26 20:05:46",
        "case_type": "緊急救護",
        "location": "台南市南區",
        "unit": "南門分隊",
        "status": "返隊中"
    },
    {
        "id": "194854",
        "datetime": "2026/02/26 19:48:54",
        "case_type": "緊急救護",
        "location": "台南市安南區",
        "unit": "安南分隊",
        "status": "返隊中"
    },
    {
        "id": "193813",
        "datetime": "2026/02/26 19:38:13",
        "case_type": "緊急救護",
        "location": "台南市白河區",
        "unit": "白河分隊",
        "status": "返隊中"
    },
    {
        "id": "193723",
        "datetime": "2026/02/26 19:37:23",
        "case_type": "火災",
        "location": "台南市東山區",
        "unit": "東山分隊",
        "status": "已返隊"
    },
    {
        "id": "192247",
        "datetime": "2026/02/26 19:22:47",
        "case_type": "緊急救護",
        "location": "台南市大內區",
        "unit": "大內分隊",
        "status": "返隊中"
    },
    {
        "id": "190718",
        "datetime": "2026/02/26 19:07:18",
        "case_type": "緊急救護",
        "location": "台南市安南區",
        "unit": "安和分隊",
        "status": "返隊中"
    },
    {
        "id": "181657",
        "datetime": "2026/02/26 18:16:57",
        "case_type": "火災",
        "location": "台南市北門區",
        "unit": "北門分隊",
        "status": "已到達"
    },
    {
        "id": "165913",
        "datetime": "2026/02/26 16:59:13",
        "case_type": "火災",
        "location": "台南市關廟區南雄南路",
        "unit": "關廟分隊",
        "status": "已返隊"
    },
    {
        "id": "164555",
        "datetime": "2026/02/26 16:45:55",
        "case_type": "火災",
        "location": "台南市南區中華南路一段",
        "unit": "南門分隊",
        "status": "已返隊"
    },
    {
        "id": "140059",
        "datetime": "2026/02/26 14:00:59",
        "case_type": "火災",
        "location": "台南市安平區運河路",
        "unit": "安平分隊",
        "status": "已返隊"
    },
    {
        "id": "085644",
        "datetime": "2026/02/26 08:56:44",
        "case_type": "火災",
        "location": "台南市東區林森路二段192巷",
        "unit": "中正分隊,公園分隊,南門分隊,大橋特搜分隊,崇善分隊,後甲分隊,復興分隊,德興分隊,東門分隊,灣裡分隊,第七大隊",
        "status": "已返隊"
    },
    {
        "id": "081138",
        "datetime": "2026/02/26 08:11:38",
        "case_type": "火災",
        "location": "台南市永康區大灣路",
        "unit": "仁德分隊,大橋特搜分隊,大灣分隊,後甲分隊,復興分隊,東門分隊,永康分隊,第五大隊",
        "status": "已返隊"
    },
    {
        "id": "105438",
        "datetime": "2026/02/24 10:54:38",
        "case_type": "火災",
        "location": "台南市南區新孝路",
        "unit": "中正分隊,南門分隊,和緯分隊,大橋特搜分隊,安南分隊,安平分隊,崇善分隊,德興分隊,東門分隊,永華分隊,灣裡分隊,第七大隊,第六大隊,第四大隊",
        "status": "已返隊"
    },
    {
        "id": "102339",
        "datetime": "2026/02/23 10:23:39",
        "case_type": "火災",
        "location": "台南市安南區永續三街",
        "unit": "中正分隊,公園分隊,和緯分隊,安南分隊,安和分隊,第六大隊",
        "status": "已返隊"
    },
    {
        "id": "044249",
        "datetime": "2026/02/23 04:42:49",
        "case_type": "火災",
        "location": "台南市新市區",
        "unit": "南科分隊,新市分隊",
        "status": "已返隊"
    },
    {
        "id": "052814",
        "datetime": "2026/02/17 05:29:14",
        "case_type": "火災",
        "location": "台南市安南區城西街３段1105巷",
        "unit": "土城分隊",
        "status": "已返隊"
    }
]