[
    {
        "id": "122935",
        "datetime": "2026/04/04 12:29:35",
        "case_type": "緊急救護",
        "location": "台南市東區",
        "unit": "東門分隊",
        "status": "已出動"
    },
    {
        "id": "122259",
        "datetime": "2026/04/04 12:23:09",
        "case_type": "緊急救護",
        "location": "台南市永康區",
        "unit": "復興分隊",
        "status": "已到達"
    },
    {
        "id": "122244",
        "datetime": "2026/04/04 12:22:44",
        "case_type": "緊急救護",
        "location": "台南市麻豆區",
        "unit": "麻豆分隊",
        "status": "已到達"
    },
    {
        "id": "121833",
        "datetime": "2026/04/04 12:18:33",
        "case_type": "緊急救護",
        "location": "台南市東區",
        "unit": "崇善分隊",
        "status": "已到達"
    },
    {
        "id": "121738",
        "datetime": "2026/04/04 12:17:38",
        "case_type": "緊急救護",
        "location": "台南市柳營區",
        "unit": "柳營分隊",
        "status": "已到達"
    },
    {
        "id": "121434",
        "datetime": "2026/04/04 12:14:34",
        "case_type": "緊急救護",
        "location": "台南市安南區",
        "unit": "安南分隊",
        "status": "送醫中"
    },
    {
        "id": "121046",
        "datetime": "2026/04/04 12:10:46",
        "case_type": "火災",
        "location": "台南市仁德區保華路",
        "unit": "文賢分隊",
        "status": "已到達"
    },
    {
        "id": "120914",
        "datetime": "2026/04/04 12:09:14",
        "case_type": "緊急救護",
        "location": "台南市山上區",
        "unit": "山上分隊",
        "status": "送醫中"
    },
    {
        "id": "120842",
        "datetime": "2026/04/04 12:08:42",
        "case_type": "緊急救護",
        "location": "台南市永康區",
        "unit": "大橋高救",
        "status": "已到院"
    },
    {
        "id": "120450",
        "datetime": "2026/04/04 12:04:50",
        "case_type": "緊急救護",
        "location": "台南市東區",
        "unit": "東門分隊",
        "status": "返隊中"
    },
    {
        "id": "120409",
        "datetime": "2026/04/04 12:04:12",
        "case_type": "緊急救護",
        "location": "台南市東區",
        "unit": "後甲分隊",
        "status": "已到院"
    },
    {
        "id": "115753",
        "datetime": "2026/04/04 11:57:53",
        "case_type": "火災",
        "location": "台南市南區同興路15巷",
        "unit": "灣裡分隊",
        "status": "已到達"
    },
    {
        "id": "115352",
        "datetime": "2026/04/04 11:53:52",
        "case_type": "緊急救護",
        "location": "台南市將軍區",
        "unit": "將軍分隊",
        "status": "返隊中"
    },
    {
        "id": "115335",
        "datetime": "2026/04/04 11:53:35",
        "case_type": "緊急救護",
        "location": "台南市永康區",
        "unit": "大灣分隊",
        "status": "已到院"
    },
    {
        "id": "114544",
        "datetime": "2026/04/04 11:45:44",
        "case_type": "緊急救護",
        "location": "台南市永康區",
        "unit": "鹽行分隊",
        "status": "返隊中"
    },
    {
        "id": "114518",
        "datetime": "2026/04/04 11:45:18",
        "case_type": "緊急救護",
        "location": "台南市南區",
        "unit": "南門分隊",
        "status": "返隊中"
    },
    {
        "id": "113924",
        "datetime": "2026/04/04 11:39:24",
        "case_type": "火災",
        "location": "台南市北區長榮路五段452巷",
        "unit": "公園分隊",
        "status": "已到達"
    },
    {
        "id": "204210",
        "datetime": "2026/04/03 20:42:10",
        "case_type": "火災",
        "location": "台南市六甲區中正路5巷",
        "unit": "下營分隊,六甲分隊,善化分隊,大內分隊,官田分隊,柳營分隊,第二大隊,麻豆分隊",
        "status": "已返隊"
    },
    {
        "id": "053053",
        "datetime": "2026/04/03 05:30:53",
        "case_type": "火災",
        "location": "台南市後壁區蘭科十九路",
        "unit": "六甲分隊,官田分隊,後壁分隊,新營分隊,東山分隊,白河分隊,麻豆分隊",
        "status": "已返隊"
    },
    {
        "id": "052556",
        "datetime": "2026/04/03 05:25:56",
        "case_type": "火災",
        "location": "台南市鹽水區",
        "unit": "下營分隊,學甲分隊,新營分隊,柳營分隊,白河分隊,第一大隊,鹽水分隊",
        "status": "已返隊"
    },
    {
        "id": "173855",
        "datetime": "2026/04/02 17:38:55",
        "case_type": "災害搶救",
        "location": "台南市東山區",
        "unit": "後壁分隊,東山分隊,白河分隊,第一大隊",
        "status": "已返隊"
    }
]