{
    "id": "135825",
    "case_type": "緊急救護",
    "location": "台南市永康區",
    "unit": "永康分隊",
    "history": [
        {
            "datetime": "2025/11/21 13:58:25",
            "status": "已出動",
            "updated": "2025/11/21 14:00:04"
        },
        {
            "datetime": "2025/11/21 13:58:25",
            "status": "已到達",
            "updated": "2025/11/21 14:10:04"
        },
        {
            "datetime": "2025/11/21 13:58:25",
            "status": "返隊中",
            "updated": "2025/11/21 14:25:03"
        },
        {
            "datetime": "2025/11/21 13:58:25",
            "status": "已返隊",
            "updated": "2025/11/21 14:30:04"
        }
    ]
}